SEQUENTIAL CIRCUITS/40.synchronous_fifo/fifo.v
module fifo
    #( parameter FIFO_DEPTH = 8,
	   parameter DATA_WIDTH = 32)
	(input clk, 
     input rst_n,
     input cs,     // chip select	 
     input wr_en, 
     input rd_en, 
     input [DATA_WIDTH-1:0] data_in, 
     output reg [DATA_WIDTH-1:0] data_out, 
	 output empty,
	 output full); 
    localparam FIFO_DEPTH_LOG = $clog2(FIFO_DEPTH);
	reg [DATA_WIDTH-1:0] fifo [0:FIFO_DEPTH-1];
	reg [FIFO_DEPTH_LOG:0] write_pointer;
	reg [FIFO_DEPTH_LOG:0] read_pointer;
    always @(posedge clk or negedge rst_n) begin
	    if(!rst_n)
		    write_pointer <= 0;
		else if (cs && wr_en && !full)
	        write_pointer <= write_pointer + 1'b1;
	end
	always @(posedge clk or negedge rst_n) begin
	    if(!rst_n)
		    read_pointer <= 0;
		else if (cs && rd_en && !empty)
	        read_pointer <= read_pointer + 1'b1;
	end
    assign empty = (read_pointer == write_pointer);
	assign full  = (read_pointer == {~write_pointer[FIFO_DEPTH_LOG], write_pointer[FIFO_DEPTH_LOG-1:0]});

    always @(posedge clk) begin
	    if (cs && wr_en && !full)
	        fifo[write_pointer[FIFO_DEPTH_LOG-1:0]] <= data_in;
	end
	
	always @(posedge clk or negedge rst_n) begin
	    if (!rst_n)
		    data_out <= 0;
		else if (cs && rd_en && !empty)
	        data_out <= fifo[read_pointer[FIFO_DEPTH_LOG-1:0]];
	end

endmodule

SEQUENTIAL CIRCUITS/40.synchronous_fifo/fifo_tb.v
module tb_fifo_sync();
	
	// Testbench variables
	parameter FIFO_DEPTH = 8;
	parameter DATA_WIDTH = 32;
    reg clk = 0; 
    reg rst_n;
    reg cs;	 
    reg wr_en;
    reg rd_en;
    reg [DATA_WIDTH-1:0] data_in;
    wire [DATA_WIDTH-1:0] data_out;
	wire empty;
	wire full;
	
    integer i;
	fifo 
	    #(.FIFO_DEPTH(FIFO_DEPTH),
	     .DATA_WIDTH(DATA_WIDTH))
        FIFO0
  	    (.clk     (clk     ), 
         .rst_n   (rst_n   ),
         .cs      (cs      ),	 
         .wr_en   (wr_en   ), 
         .rd_en   (rd_en   ), 
         .data_in (data_in ), 
         .data_out(data_out), 
	     .empty   (empty   ),
	     .full    (full    ));

    task write_data(input [DATA_WIDTH-1:0] d_in);
	    begin
		    @(posedge clk); // sync to positive edge of clock
			cs = 1; wr_en = 1;
			data_in = d_in;
			$display($time, " write_data data_in = %0d", data_in);
			@(posedge clk);
		    cs = 1; wr_en = 0;
		end
	endtask
	
	task read_data();
	    begin
		    @(posedge clk);  // sync to positive edge of clock
			cs = 1; rd_en = 1;
			@(posedge clk);
			#0.1;
		    $display($time, " read_data data_out = %0d", data_out);
		    cs = 1; rd_en = 0;
		end
	endtask
	always begin #0.5 clk = ~clk; end
	
    initial begin
	 $dumpfile("fifo.vcd");
	 $dumpvars;
	
	    #1; 
		rst_n = 0; rd_en = 0; wr_en = 0;
		
		#1.3; 
		rst_n = 1;
		$display($time, "\n SCENARIO 1");
		write_data(1);
		write_data(10);
		write_data(100);
		read_data();
		read_data();
		read_data();
		read_data();
		
        $display($time, "\n SCENARIO 2");
		for (i=0; i<FIFO_DEPTH; i=i+1) begin
		    write_data(2**i);
			read_data();        
		end

        $display($time, "\n SCENARIO 3");		
		for (i=0; i<=FIFO_DEPTH; i=i+1) begin
		    write_data(2**i);
		end
		
		for (i=0; i<FIFO_DEPTH; i=i+1) begin
			read_data();
		end
		
	    #40 $stop;
	end
endmodule

SEQUENTIAL CIRCUITS/40.synchronous_fifo/fifo.vcd
$date
	Tue Feb  7 10:41:19 2023
$end
$version
	Icarus Verilog
$end
$timescale
	1s
$end
$scope module tb_fifo_sync $end
$var wire 1 ! full $end
$var wire 1 " empty $end
$var wire 32 # data_out [31:0] $end
$var reg 1 $ clk $end
$var reg 1 % cs $end
$var reg 32 & data_in [31:0] $end
$var reg 1 ' rd_en $end
$var reg 1 ( rst_n $end
$var reg 1 ) wr_en $end
$var integer 32 * i [31:0] $end
$scope module FIFO0 $end
$var wire 1 $ clk $end
$var wire 1 % cs $end
$var wire 32 + data_in [31:0] $end
$var wire 1 ' rd_en $end
$var wire 1 ( rst_n $end
$var wire 1 ) wr_en $end
$var wire 1 ! full $end
$var wire 1 " empty $end
$var reg 32 , data_out [31:0] $end
$var reg 4 - read_pointer [3:0] $end
$var reg 4 . write_pointer [3:0] $end
$upscope $end
$scope task read_data $end
$upscope $end
$scope task write_data $end
$var reg 32 / d_in [31:0] $end
$upscope $end
$upscope $end
$enddefinitions $end
#0
$dumpvars
bx /
bx .
bx -
bx ,
bx +
bx *
x)
x(
x'
bx &
x%
0$
bx #
x"
x!
$end
#1
0!
1"
b0 .
b0 -
b0 #
b0 ,
0)
0'
0(
1$
#2
b1 /
1(
0$
#3
0"
b1 .
b1 &
b1 +
1)
1%
1$
#4
0$
#5
b1010 /
0)
1$
#6
0$
#7
b10 .
b1010 &
b1010 +
1)
1$
#8
0$
#9
b1100100 /
0)
1$
#10
0$
#11
b11 .
b1100100 &
b1100100 +
1)
1$
#12
0$
#13
0)
1$
#14
0$
#15
b1 #
b1 ,
b1 -
1'
1$
#16
0$
#17
b10 -
b1010 #
b1010 ,
0'
1$
#18
0$
#19
b1100100 #
b1100100 ,
1"
b11 -
1'
1$
#20
0$
#21
0'
1$
#22
0$
#23
1'
1$
#24
0$
#25
0'
1$
#26
0$
#27
1'
1$
#28
0$
#29
b1 /
b0 *
0'
1$
#30
0$
#31
0"
b100 .
b1 &
b1 +
1)
1$
#32
0$
#33
0)
1$
#34
0$
#35
b1 #
b1 ,
1"
b100 -
1'
1$
#36
0$
#37
b10 /
b1 *
0'
1$
#38
0$
#39
0"
b101 .
b10 &
b10 +
1)
1$
#40
0$
#41
0)
1$
#42
0$
#43
b10 #
b10 ,
1"
b101 -
1'
1$
#44
0$
#45
b100 /
b10 *
0'
1$
#46
0$
#47
0"
b110 .
b100 &
b100 +
1)
1$
#48
0$
#49
0)
1$
#50
0$
#51
b100 #
b100 ,
1"
b110 -
1'
1$
#52
0$
#53
b1000 /
b11 *
0'
1$
#54
0$
#55
0"
b111 .
b1000 &
b1000 +
1)
1$
#56
0$
#57
0)
1$
#58
0$
#59
b1000 #
b1000 ,
1"
b111 -
1'
1$
#60
0$
#61
b10000 /
b100 *
0'
1$
#62
0$
#63
0"
b1000 .
b10000 &
b10000 +
1)
1$
#64
0$
#65
0)
1$
#66
0$
#67
b10000 #
b10000 ,
1"
b1000 -
1'
1$
#68
0$
#69
b100000 /
b101 *
0'
1$
#70
0$
#71
0"
b1001 .
b100000 &
b100000 +
1)
1$
#72
0$
#73
0)
1$
#74
0$
#75
b100000 #
b100000 ,
1"
b1001 -
1'
1$
#76
0$
#77
b1000000 /
b110 *
0'
1$
#78
0$
#79
0"
b1010 .
b1000000 &
b1000000 +
1)
1$
#80
0$
#81
0)
1$
#82
0$
#83
b1000000 #
b1000000 ,
1"
b1010 -
1'
1$
#84
0$
#85
b10000000 /
b111 *
0'
1$
#86
0$
#87
0"
b1011 .
b10000000 &
b10000000 +
1)
1$
#88
0$
#89
0)
1$
#90
0$
#91
b10000000 #
b10000000 ,
1"
b1011 -
1'
1$
#92
0$
#93
b1 /
b0 *
0'
1$
#94
0$
#95
0"
b1100 .
b1 &
b1 +
1)
1$
#96
0$
#97
b10 /
b1 *
0)
1$
#98
0$
#99
b1101 .
b10 &
b10 +
1)
1$
#100
0$
#101
b100 /
b10 *
0)
1$
#102
0$
#103
b1110 .
b100 &
b100 +
1)
1$
#104
0$
#105
b1000 /
b11 *
0)
1$
#106
0$
#107
b1111 .
b1000 &
b1000 +
1)
1$
#108
0$
#109
b10000 /
b100 *
0)
1$
#110
0$
#111
b0 .
b10000 &
b10000 +
1)
1$
#112
0$
#113
b100000 /
b101 *
0)
1$
#114
0$
#115
b1 .
b100000 &
b100000 +
1)
1$
#116
0$
#117
b1000000 /
b110 *
0)
1$
#118
0$
#119
b10 .
b1000000 &
b1000000 +
1)
1$
#120
0$
#121
b10000000 /
b111 *
0)
1$
#122
0$
#123
1!
b11 .
b10000000 &
b10000000 +
1)
1$
#124
0$
#125
b100000000 /
b1000 *
0)
1$
#126
0$
#127
b100000000 &
b100000000 +
1)
1$
#128
0$
#129
b0 *
0)
1$
#130
0$
#131
b1 #
b1 ,
0!
b1100 -
1'
1$
#132
0$
#133
b1101 -
b10 #
b10 ,
b1 *
0'
1$
#134
0$
#135
b100 #
b100 ,
b1110 -
1'
1$
#136
0$
#137
b1111 -
b1000 #
b1000 ,
b10 *
0'
1$
#138
0$
#139
b10000 #
b10000 ,
b0 -
1'
1$
#140
0$
#141
b1 -
b100000 #
b100000 ,
b11 *
0'
1$
#142
0$
#143
b1000000 #
b1000000 ,
b10 -
1'
1$
#144
0$
#145
1"
b11 -
b10000000 #
b10000000 ,
b100 *
0'
1$
#146
0$
#147
1'
1$
#148
0$
#149
b101 *
0'
1$
#150
0$
#151
1'
1$
#152
0$
#153
b110 *
0'
1$
#154
0$
#155
1'
1$
#156
0$
#157
b111 *
0'
1$
#158
0$
#159
1'
1$
#160
0$
#161
b1000 *
0'
1$
