SEQUENTIAL CIRCUITS/6.updown_counter/updown.v
module updown(
    Clk,
    reset,
    UpOrDown,
    Count
    );
    input Clk,reset,UpOrDown;
    output [3: 0] Count;
    reg [3 : 0] Count = 0;  
    always @(posedge(Clk))
     begin
        if(reset == 1) 
            Count <= 0;
        else  
            if(UpOrDown == 1)   
                if(Count == 11)
                    Count <= 0;
                else
                    Count <= Count + 1; 
            else  
                if(Count == 0)
                    Count <= 11;
                else
                    Count <= Count - 1;      end    
    
endmodule

SEQUENTIAL CIRCUITS/41.mod_12_counter/mod_12_counter_tb.v
module updown_tb;
    reg Clk;
    reg reset;
    reg UpOrDown;
    wire [3:0] Count;
    updown uut ( .Clk(Clk), .reset(reset), .UpOrDown(UpOrDown), .Count(Count));
    initial Clk = 0;
    always #5 Clk = ~Clk;
    initial begin #2 reset =1; end
    initial begin
      $dumpfile("modcounter.vcd");
      $dumpvars;
	   
       #5 reset = 0;
      #20  UpOrDown = 0;
      #50 UpOrDown = 1;
       #100 UpOrDown = 0;  
    end
    initial begin #120 $finish; end
      
endmodule

SEQUENTIAL CIRCUITS/41.mod_12_counter/modcounter.vcd
$date
	Tue Feb  7 10:44:49 2023
$end
$version
	Icarus Verilog
$end
$timescale
	1s
$end
$scope module updown_tb $end
$var wire 4 ! Count [3:0] $end
$var reg 1 " Clk $end
$var reg 1 # UpOrDown $end
$var reg 1 $ reset $end
$scope module uut $end
$var wire 1 " Clk $end
$var wire 1 # UpOrDown $end
$var wire 1 $ reset $end
$var reg 4 % Count [3:0] $end
$upscope $end
$upscope $end
$enddefinitions $end
#0
$dumpvars
b0 %
x$
x#
0"
b0 !
$end
#2
1$
#5
b1011 !
b1011 %
0$
1"
#10
0"
#15
b1010 !
b1010 %
1"
#20
0"
#25
b1001 !
b1001 %
1"
0#
#30
0"
#35
b1000 !
b1000 %
1"
#40
0"
#45
b111 !
b111 %
1"
#50
0"
#55
b110 !
b110 %
1"
#60
0"
#65
b101 !
b101 %
1"
#70
0"
#75
b110 !
b110 %
1"
1#
#80
0"
#85
b111 !
b111 %
1"
#90
0"
#95
b1000 !
b1000 %
1"
#100
0"
#105
b1001 !
b1001 %
1"
#110
0"
#115
b1010 !
b1010 %
1"
