SEQUENTIAL CIRCUITS/37.D_ff_sync/dff.v
module dff_sync(d,clk,rst,q );
input d,clk,rst;
output reg q;

always @(posedge clk)
begin
        if(rst)
        q<=1'b0;
        else
        q<= d;
end

endmodule

SEQUENTIAL CIRCUITS/37.D_ff_sync/dff_tb.v
module testbench;
reg clk,rst,d;
wire q;
dff_sync uut(.clk(clk),.d(d),.rst(rst),.q(q));

initial
begin
d=0;
clk=0;
rst=1;
end 
 always #5 clk=~clk;
 initial
 begin
	$dumpfile("d_ff.vcd");
	$dumpvars;
 #10 rst =0;
 #10 d=1'b1;
 #10 d=1'b1;
 #10 d=1'b0;
 #10 d=1'b0;
 #10 d=1'b1;
 #10 d=1'b0;
 #10 d=1'b1;
 end
 
initial 
#100 $finish();



endmodule

SEQUENTIAL CIRCUITS/37.D_ff_sync/d_ff.vcd
$date
	Tue Feb  7 10:20:35 2023
$end
$version
	Icarus Verilog
$end
$timescale
	1s
$end
$scope module testbench $end
$var wire 1 ! q $end
$var reg 1 " clk $end
$var reg 1 # d $end
$var reg 1 $ rst $end
$scope module uut $end
$var wire 1 " clk $end
$var wire 1 # d $end
$var wire 1 $ rst $end
$var reg 1 ! q $end
$upscope $end
$upscope $end
$enddefinitions $end
#0
$dumpvars
1$
0#
0"
x!
$end
#5
0!
1"
#10
0"
0$
#15
1"
#20
0"
1#
#25
1!
1"
#30
0"
#35
1"
#40
0"
0#
#45
0!
1"
#50
0"
#55
1"
#60
0"
1#
#65
1!
1"
#70
0"
0#
#75
0!
1"
#80
0"
1#
#85
1!
1"
