COMBINATIONAL CIRCUITS/29.16*1_mux/mux.v
module n_1mux(in,sel,y);
parameter n=16;
input [n-1:0] in;
input [3:0] sel;
output reg y;

always @(in or sel)
begin
case(sel)
4'b0000: y= in[0];
4'b0001: y= in[1];
4'b0010: y= in[2];
4'b0011: y= in[3];
4'b0100: y= in[4];
4'b0101: y= in[5];
4'b0110: y= in[6];
4'b0111: y= in[7];
4'b1000: y= in[8];
4'b1001: y= in[9];
4'b1010: y= in[10];
4'b1011: y= in[11];
4'b1100: y= in[12];
4'b1101: y= in[13];
4'b1110: y= in[14];
4'b1111: y= in[n-1];
default: y=4'b0000;
endcase
end
endmodule

COMBINATIONAL CIRCUITS/29.16*1_mux/mux_tb.v
module n_1mux_tb;
	reg [15:0] in;
	reg [3:0] sel;
	wire y;
	n_1mux uut (
		.in(in), 
		.sel(sel), 
		.y(y)
	);
initial begin
in=16'b1000000000000000; sel=4'b0000; 
#10 in=16'b0100000000000010; sel=4'b0001; 
#10 in=16'b0010000000000100; sel=4'b0010;
#10 in=16'b0001000000000000; sel=4'b0011;
#10 in=16'b0000010000000000; sel=4'b0101; 
#10 in=16'b0000001000000000; sel=4'b0110;
#10 in=16'b0000000111100000; sel=4'b0111;
#10 in=16'b0000000010000000; sel=4'b1000;
#10 in=16'b0000000001000000; sel=4'b1001;
#10 in=16'b0000011000100000; sel=4'b1010; 
#10 in=16'b0000000000010000; sel=4'b1011;
#10 in=16'b0000000000001000; sel=4'b1100; 
#10 in=16'b0000000000000100; sel=4'b1101; 
#10 in=16'b0000000000000010; sel=4'b1110; 
#10 in=16'b1000000000000001; sel=4'b1111;
end 
initial
begin
$dumpfile("mux.vcd");
$dumpvars;
$monitor("in=%b | sel=%b | out=%b", in,sel,y);
				 
#500 $finish;

end
      
endmodule

COMBINATIONAL CIRCUITS/29.16*1_mux/mux.vcd
$date
	Mon Feb 13 21:23:21 2023
$end
$version
	Icarus Verilog
$end
$timescale
	1s
$end
$scope module n_1mux_tb $end
$var wire 1 ! y $end
$var reg 16 " in [15:0] $end
$var reg 4 # sel [3:0] $end
$scope module uut $end
$var wire 16 $ in [15:0] $end
$var wire 4 % sel [3:0] $end
$var reg 1 ! y $end
$upscope $end
$upscope $end
$enddefinitions $end
#0
$dumpvars
b0 %
b1000000000000000 $
b0 #
b1000000000000000 "
0!
$end
#10
1!
b1 #
b1 %
b100000000000010 "
b100000000000010 $
#20
b10 #
b10 %
b10000000000100 "
b10000000000100 $
#30
0!
b11 #
b11 %
b1000000000000 "
b1000000000000 $
#40
b101 #
b101 %
b10000000000 "
b10000000000 $
#50
b110 #
b110 %
b1000000000 "
b1000000000 $
#60
1!
b111 #
b111 %
b111100000 "
b111100000 $
#70
0!
b1000 #
b1000 %
b10000000 "
b10000000 $
#80
b1001 #
b1001 %
b1000000 "
b1000000 $
#90
1!
b1010 #
b1010 %
b11000100000 "
b11000100000 $
#100
0!
b1011 #
b1011 %
b10000 "
b10000 $
#110
b1100 #
b1100 %
b1000 "
b1000 $
#120
b1101 #
b1101 %
b100 "
b100 $
#130
b1110 #
b1110 %
b10 "
b10 $
#140
1!
b1111 #
b1111 %
b1000000000000001 "
b1000000000000001 $
