COMBINATIONAL CIRCUITS/28.mux_8x1/mux.v
module m81(out, D0, D1, D2, D3, D4, D5, D6, D7, S0, S1, S2);
input wire D0, D1, D2, D3, D4, D5, D6, D7, S0, S1, S2;
output reg out;
always@(*)
begin
case(S0 & S1 & S2)
3'b000: out=D0;
3'b001: out=D1;
3'b010: out=D2;
3'b011: out=D3;
3'b100: out=D4;
3'b101: out=D5;
3'b110: out=D6;
3'b111: out=D7;
default: out=1'b0;
endcase
end
endmodule

COMBINATIONAL CIRCUITS/28.mux_8x1/mux_tb.v
module mux81_tb; 
wire out;
reg D0, D1, D2, D3, D4, D5, D6, D7, D8, S0, S1, S2;
m81 name(.D0(D0), .D1(D1), .D2(D2), .D3(D3), .D4(D4), .D5(D5), .D6(D6), .D7(D7), .S0(S0), .S1(S1), .S2(S2), .out(out)); 
initial 
begin
	$dumpfile("mux.vcd");
	$dumpvars;
D0=1'b0; D1=1'b0; D2=1'b0; D3=1'b0; D4=1'b0; D5=1'b0; D6=1'b0; D7=1'b0;S0=1'b0; S1=1'b0; S2=1'b0; 
#500 $finish; 
end 
always #1 D0=~D0;
always #2 D1=~D1;
always #3 D2=~D2;
always #4 D3=~D3;
always #5 D4=~D4;
always #6 D5=~D5;
always #7 D6=~D6;
always #8 D7=~D7;
always #9 S0=~S0;
always #10 S1=~S1;
always #11 S2=~S2;
always@(D0 or D1 or D2 or D3 or D4 or D5 or D6 or D7 or S0 or S1 or S2) 
$monitor("At time = %t, Output = %d", $time, out); 
endmodule

COMBINATIONAL CIRCUITS/28.mux_8x1/mux.vcd
$date
	Tue Feb  7 11:21:06 2023
$end
$version
	Icarus Verilog
$end
$timescale
	1s
$end
$scope module mux81_tb $end
$var wire 1 ! out $end
$var reg 1 " D0 $end
$var reg 1 # D1 $end
$var reg 1 $ D2 $end
$var reg 1 % D3 $end
$var reg 1 & D4 $end
$var reg 1 ' D5 $end
$var reg 1 ( D6 $end
$var reg 1 ) D7 $end
$var reg 1 * S0 $end
$var reg 1 + S1 $end
$var reg 1 , S2 $end
$scope module name $end
$var wire 1 " D0 $end
$var wire 1 # D1 $end
$var wire 1 $ D2 $end
$var wire 1 % D3 $end
$var wire 1 & D4 $end
$var wire 1 ' D5 $end
$var wire 1 ( D6 $end
$var wire 1 ) D7 $end
$var wire 1 * S0 $end
$var wire 1 + S1 $end
$var wire 1 , S2 $end
$var reg 1 ! out $end
$upscope $end
$upscope $end
$enddefinitions $end
#0
$dumpvars
0,
0+
0*
0)
0(
0'
0&
0%
0$
0#
0"
0!
$end
#1
1!
1"
#2
0!
0"
1#
#3
1!
1"
1$
#4
0!
0"
0#
1%
#5
1!
1"
1&
#6
0!
0"
1#
0$
1'
#7
1!
1"
1(
#8
0!
0"
0#
0%
1)
#9
1!
1"
1$
1*
#10
0!
0"
1#
0&
1+
#11
1!
1"
1,
#12
0!
0"
0#
0$
1%
0'
#13
1"
#14
1!
0"
1#
0(
#15
1"
1$
1&
#16
0!
0"
0#
0%
0)
#17
1"
#18
0"
1#
0$
1'
0*
#19
1!
1"
#20
0!
0"
0#
1%
0&
0+
#21
1!
1"
1$
1(
#22
0!
0"
1#
0,
#23
1!
1"
#24
0!
0"
0#
0$
0%
0'
1)
#25
1!
1"
1&
#26
0!
0"
1#
#27
1!
1"
1$
1*
#28
0!
0"
0#
1%
0(
#29
1!
1"
#30
0!
0"
1#
0$
0&
1'
1+
#31
1!
1"
#32
0!
0"
0#
0%
0)
#33
1"
1$
1,
#34
1!
0"
1#
#35
1"
1&
1(
#36
0!
0"
0#
0$
1%
0'
0*
#37
1!
1"
#38
0!
0"
1#
#39
1!
1"
1$
#40
0!
0"
0#
0%
0&
1)
0+
#41
1!
1"
#42
0!
0"
1#
0$
1'
0(
#43
1!
1"
#44
0!
0"
0#
1%
0,
#45
1!
1"
1$
1&
1*
#46
0!
0"
1#
#47
1!
1"
#48
0!
0"
0#
0$
0%
0'
0)
#49
1!
1"
1(
#50
0!
0"
1#
0&
1+
#51
1!
1"
1$
#52
0!
0"
0#
1%
#53
1!
1"
#54
0!
0"
1#
0$
1'
0*
#55
1!
1"
1&
1,
#56
0!
0"
0#
0%
0(
1)
#57
1!
1"
1$
#58
0!
0"
1#
#59
1!
1"
#60
0!
0"
0#
0$
1%
0&
0'
0+
#61
1!
1"
#62
0!
0"
1#
#63
1!
1"
1$
1(
1*
#64
0!
0"
0#
0%
0)
#65
1!
1"
1&
#66
0!
0"
1#
0$
1'
0,
#67
1!
1"
#68
0!
0"
0#
1%
#69
1!
1"
1$
#70
0!
0"
1#
0&
0(
1+
#71
1!
1"
#72
0!
0"
0#
0$
0%
0'
1)
0*
#73
1!
1"
#74
0!
0"
1#
#75
1!
1"
1$
1&
#76
0!
0"
0#
1%
#77
1!
1"
1(
1,
#78
0!
0"
1#
0$
1'
#79
1!
1"
#80
0!
0"
0#
0%
0&
0)
0+
#81
1!
1"
1$
1*
#82
0!
0"
1#
#83
1!
1"
#84
0!
0"
0#
0$
1%
0'
0(
#85
1!
1"
1&
#86
0!
0"
1#
#87
1!
1"
1$
#88
0!
0"
0#
0%
1)
0,
#89
1!
1"
#90
0!
0"
1#
0$
0&
1'
0*
1+
#91
1!
1"
1(
#92
0!
0"
0#
1%
#93
1!
1"
1$
#94
0!
0"
1#
#95
1!
1"
1&
#96
0!
0"
0#
0$
0%
0'
0)
#97
1!
1"
#98
0!
0"
1#
0(
#99
1!
1"
1$
1*
1,
#100
0!
0"
0#
1%
0&
0+
#101
1!
1"
#102
0!
0"
1#
0$
1'
#103
1!
1"
#104
0!
0"
0#
0%
1)
#105
1!
1"
1$
1&
1(
#106
0!
0"
1#
#107
1!
1"
#108
0!
0"
0#
0$
1%
0'
0*
#109
1!
1"
#110
0!
0"
1#
0&
1+
0,
#111
1!
1"
1$
#112
0!
0"
0#
0%
0(
0)
#113
1!
1"
#114
0!
0"
1#
0$
1'
#115
1!
1"
1&
#116
0!
0"
0#
1%
#117
1!
1"
1$
1*
#118
0!
0"
1#
#119
1!
1"
1(
#120
0!
0"
0#
0$
0%
0&
0'
1)
0+
#121
1!
1"
1,
#122
0!
0"
1#
#123
1!
1"
1$
#124
0!
0"
0#
1%
#125
1!
1"
1&
#126
0!
0"
1#
0$
1'
0(
0*
#127
1!
1"
#128
0!
0"
0#
0%
0)
#129
1!
1"
1$
#130
0!
0"
1#
0&
1+
#131
1!
1"
#132
0!
0"
0#
0$
1%
0'
0,
#133
1!
1"
1(
#134
0!
0"
1#
#135
1!
1"
1$
1&
1*
#136
0!
0"
0#
0%
1)
#137
1!
1"
#138
0!
0"
1#
0$
1'
#139
1!
1"
#140
0!
0"
0#
1%
0&
0(
0+
#141
1!
1"
1$
#142
0!
0"
1#
#143
1!
1"
1,
#144
0!
0"
0#
0$
0%
0'
0)
0*
#145
1!
1"
1&
#146
0!
0"
1#
#147
1!
1"
1$
1(
#148
0!
0"
0#
1%
#149
1!
1"
#150
0!
0"
1#
0$
0&
1'
1+
#151
1!
1"
#152
0!
0"
0#
0%
1)
#153
1"
1$
1*
#154
0"
1#
0(
0,
#155
1!
1"
1&
#156
0!
0"
0#
0$
1%
0'
#157
1!
1"
#158
0!
0"
1#
#159
1!
1"
1$
#160
0!
0"
0#
0%
0&
0)
0+
#161
1!
1"
1(
#162
0!
0"
1#
0$
1'
0*
#163
1!
1"
#164
0!
0"
0#
1%
#165
1!
1"
1$
1&
1,
#166
0!
0"
1#
#167
1!
1"
#168
0!
0"
0#
0$
0%
0'
0(
1)
#169
1!
1"
#170
0!
0"
1#
0&
1+
#171
1!
1"
1$
1*
#172
0!
0"
0#
1%
#173
1"
#174
1!
0"
1#
0$
1'
#175
1"
1&
1(
#176
0!
0"
0#
0%
0)
0,
#177
1!
1"
1$
#178
0!
0"
1#
#179
1!
1"
#180
0!
0"
0#
0$
1%
0&
0'
0*
0+
#181
1!
1"
#182
0!
0"
1#
0(
#183
1!
1"
1$
#184
0!
0"
0#
0%
1)
#185
1!
1"
1&
#186
0!
0"
1#
0$
1'
#187
1!
1"
1,
#188
0!
0"
0#
1%
#189
1!
1"
1$
1(
1*
#190
0"
1#
0&
1+
#191
1"
#192
0!
0"
0#
0$
0%
0'
0)
#193
1"
#194
1!
0"
1#
#195
1"
1$
1&
#196
0!
0"
0#
1%
0(
#197
1"
#198
0"
1#
0$
1'
0*
0,
#199
1!
1"
#200
0!
0"
0#
0%
0&
1)
0+
#201
1!
1"
1$
#202
0!
0"
1#
#203
1!
1"
1(
#204
0!
0"
0#
0$
1%
0'
#205
1!
1"
1&
#206
0!
0"
1#
#207
1!
1"
1$
1*
#208
0!
0"
0#
0%
0)
#209
1!
1"
1,
#210
0"
1#
0$
0&
1'
0(
1+
#211
1"
#212
0!
0"
0#
1%
#213
1"
1$
#214
1!
0"
1#
#215
1"
1&
#216
0!
0"
0#
0$
0%
0'
1)
0*
#217
1!
1"
1(
#218
0!
0"
1#
#219
1!
1"
1$
#220
0!
0"
0#
1%
0&
0+
0,
#221
1!
1"
#222
0!
0"
1#
0$
1'
#223
1!
1"
#224
0!
0"
0#
0%
0(
0)
#225
1!
1"
1$
1&
1*
#226
0!
0"
1#
#227
1!
1"
#228
0!
0"
0#
0$
1%
0'
#229
1!
1"
#230
0!
0"
1#
0&
1+
#231
1!
1"
1$
1(
1,
#232
0!
0"
0#
0%
1)
#233
1"
#234
0"
1#
0$
1'
0*
#235
1!
1"
1&
#236
0!
0"
0#
1%
#237
1!
1"
1$
#238
0!
0"
1#
0(
#239
1!
1"
#240
0!
0"
0#
0$
0%
0&
0'
0)
0+
#241
1!
1"
#242
0!
0"
1#
0,
#243
1!
1"
1$
1*
#244
0!
0"
0#
1%
#245
1!
1"
1&
1(
#246
0!
0"
1#
0$
1'
#247
1!
1"
#248
0!
0"
0#
0%
1)
#249
1!
1"
1$
#250
0!
0"
1#
0&
1+
#251
1!
1"
#252
0!
0"
0#
0$
1%
0'
0(
0*
#253
1!
1"
1,
#254
0!
0"
1#
#255
1!
1"
1$
1&
#256
0!
0"
0#
0%
0)
#257
1!
1"
#258
0!
0"
1#
0$
1'
#259
1!
1"
1(
#260
0!
0"
0#
1%
0&
0+
#261
1!
1"
1$
1*
#262
0!
0"
1#
#263
1!
1"
#264
0!
0"
0#
0$
0%
0'
1)
0,
#265
1!
1"
1&
#266
0!
0"
1#
0(
#267
1!
1"
1$
#268
0!
0"
0#
1%
#269
1!
1"
#270
0!
0"
1#
0$
0&
1'
0*
1+
#271
1!
1"
#272
0!
0"
0#
0%
0)
#273
1!
1"
1$
1(
#274
0!
0"
1#
#275
1!
1"
1&
1,
#276
0!
0"
0#
0$
1%
0'
#277
1!
1"
#278
0!
0"
1#
#279
1!
1"
1$
1*
#280
0!
0"
0#
0%
0&
0(
1)
0+
#281
1!
1"
#282
0!
0"
1#
0$
1'
#283
1!
1"
#284
0!
0"
0#
1%
#285
1!
1"
1$
1&
#286
0!
0"
1#
0,
#287
1!
1"
1(
#288
0!
0"
0#
0$
0%
0'
0)
0*
#289
1!
1"
#290
0!
0"
1#
0&
1+
#291
1!
1"
1$
#292
0!
0"
0#
1%
#293
1!
1"
#294
0!
0"
1#
0$
1'
0(
#295
1!
1"
1&
#296
0!
0"
0#
0%
1)
#297
1"
1$
1*
1,
#298
1!
0"
1#
#299
1"
#300
0!
0"
0#
0$
1%
0&
0'
0+
#301
1!
1"
1(
#302
0!
0"
1#
#303
1!
1"
1$
#304
0!
0"
0#
0%
0)
#305
1!
1"
1&
#306
0!
0"
1#
0$
1'
0*
#307
1!
1"
#308
0!
0"
0#
1%
0(
0,
#309
1!
1"
1$
#310
0!
0"
1#
0&
1+
#311
1!
1"
#312
0!
0"
0#
0$
0%
0'
1)
#313
1!
1"
#314
0!
0"
1#
#315
1!
1"
1$
1&
1(
1*
#316
0!
0"
0#
1%
#317
1!
1"
#318
0!
0"
1#
0$
1'
#319
1!
1"
1,
#320
0!
0"
0#
0%
0&
0)
0+
#321
1!
1"
1$
#322
0!
0"
1#
0(
#323
1!
1"
#324
0!
0"
0#
0$
1%
0'
0*
#325
1!
1"
1&
#326
0!
0"
1#
#327
1!
1"
1$
#328
0!
0"
0#
0%
1)
#329
1!
1"
1(
#330
0!
0"
1#
0$
0&
1'
1+
0,
#331
1!
1"
#332
0!
0"
0#
1%
#333
1!
1"
1$
1*
#334
0!
0"
1#
#335
1!
1"
1&
#336
0!
0"
0#
0$
0%
0'
0(
0)
#337
1!
1"
#338
0!
0"
1#
#339
1!
1"
1$
#340
0!
0"
0#
1%
0&
0+
#341
1!
1"
1,
#342
0!
0"
1#
0$
1'
0*
#343
1!
1"
1(
#344
0!
0"
0#
0%
1)
#345
1!
1"
1$
1&
#346
0!
0"
1#
#347
1!
1"
#348
0!
0"
0#
0$
1%
0'
#349
1!
1"
#350
0!
0"
1#
0&
0(
1+
#351
1!
1"
1$
1*
#352
0!
0"
0#
0%
0)
0,
#353
1!
1"
#354
0!
0"
1#
0$
1'
#355
1!
1"
1&
#356
0!
0"
0#
1%
#357
1!
1"
1$
1(
#358
0!
0"
1#
#359
1!
1"
#360
0!
0"
0#
0$
0%
0&
0'
1)
0*
0+
#361
1!
1"
#362
0!
0"
1#
#363
1!
1"
1$
1,
#364
0!
0"
0#
1%
0(
#365
1!
1"
1&
#366
0!
0"
1#
0$
1'
#367
1!
1"
#368
0!
0"
0#
0%
0)
#369
1!
1"
1$
1*
#370
0"
1#
0&
1+
#371
1"
1(
#372
0!
0"
0#
0$
1%
0'
#373
1"
#374
0"
1#
0,
#375
1!
1"
1$
1&
#376
0!
0"
0#
0%
1)
#377
1!
1"
#378
0!
0"
1#
0$
1'
0(
0*
#379
1!
1"
#380
0!
0"
0#
1%
0&
0+
#381
1!
1"
1$
#382
0!
0"
1#
#383
1!
1"
#384
0!
0"
0#
0$
0%
0'
0)
#385
1!
1"
1&
1(
1,
#386
0!
0"
1#
#387
1!
1"
1$
1*
#388
0!
0"
0#
1%
#389
1!
1"
#390
0"
1#
0$
0&
1'
1+
#391
1"
#392
0!
0"
0#
0%
0(
1)
#393
1"
1$
#394
1!
0"
1#
#395
1"
1&
#396
0!
0"
0#
0$
1%
0'
0*
0,
#397
1!
1"
#398
0!
0"
1#
#399
1!
1"
1$
1(
#400
0!
0"
0#
0%
0&
0)
0+
#401
1!
1"
#402
0!
0"
1#
0$
1'
#403
1!
1"
#404
0!
0"
0#
1%
#405
1!
1"
1$
1&
1*
#406
0!
0"
1#
0(
#407
1!
1"
1,
#408
0!
0"
0#
0$
0%
0'
1)
#409
1!
1"
#410
0"
1#
0&
1+
#411
1"
1$
#412
0!
0"
0#
1%
#413
1"
1(
#414
0"
1#
0$
1'
0*
#415
1!
1"
1&
#416
0!
0"
0#
0%
0)
#417
1!
1"
1$
#418
0!
0"
1#
0,
#419
1!
1"
#420
0!
0"
0#
0$
1%
0&
0'
0(
0+
#421
1!
1"
#422
0!
0"
1#
#423
1!
1"
1$
1*
#424
0!
0"
0#
0%
1)
#425
1!
1"
1&
#426
0!
0"
1#
0$
1'
#427
1!
1"
1(
#428
0!
0"
0#
1%
#429
1!
1"
1$
1,
#430
0"
1#
0&
1+
#431
1"
#432
0!
0"
0#
0$
0%
0'
0)
0*
#433
1!
1"
#434
0!
0"
1#
0(
#435
1!
1"
1$
1&
#436
0!
0"
0#
1%
#437
1!
1"
#438
0!
0"
1#
0$
1'
#439
1!
1"
#440
0!
0"
0#
0%
0&
1)
0+
0,
#441
1!
1"
1$
1(
1*
#442
0!
0"
1#
#443
1!
1"
#444
0!
0"
0#
0$
1%
0'
#445
1!
1"
1&
#446
0!
0"
1#
#447
1!
1"
1$
#448
0!
0"
0#
0%
0(
0)
#449
1!
1"
#450
0!
0"
1#
0$
0&
1'
0*
1+
#451
1!
1"
1,
#452
0!
0"
0#
1%
#453
1!
1"
1$
#454
0!
0"
1#
#455
1!
1"
1&
1(
#456
0!
0"
0#
0$
0%
0'
1)
#457
1!
1"
#458
0!
0"
1#
#459
1!
1"
1$
1*
#460
0!
0"
0#
1%
0&
0+
#461
1!
1"
#462
0!
0"
1#
0$
1'
0(
0,
#463
1!
1"
#464
0!
0"
0#
0%
0)
#465
1!
1"
1$
1&
#466
0!
0"
1#
#467
1!
1"
#468
0!
0"
0#
0$
1%
0'
0*
#469
1!
1"
1(
#470
0!
0"
1#
0&
1+
#471
1!
1"
1$
#472
0!
0"
0#
0%
1)
#473
1!
1"
1,
#474
0!
0"
1#
0$
1'
#475
1!
1"
1&
#476
0!
0"
0#
1%
0(
#477
1"
1$
1*
#478
1!
0"
1#
#479
1"
#480
0!
0"
0#
0$
0%
0&
0'
0)
0+
#481
1!
1"
#482
0!
0"
1#
#483
1!
1"
1$
1(
#484
0!
0"
0#
1%
0,
#485
1!
1"
1&
#486
0!
0"
1#
0$
1'
0*
#487
1!
1"
#488
0!
0"
0#
0%
1)
#489
1!
1"
1$
#490
0!
0"
1#
0&
0(
1+
#491
1!
1"
#492
0!
0"
0#
0$
1%
0'
#493
1!
1"
#494
0!
0"
1#
#495
1!
1"
1$
1&
1*
1,
#496
0!
0"
0#
0%
0)
#497
1"
1(
#498
1!
0"
1#
0$
1'
#499
1"
#500
0!
0"
0#
1%
0&
0+
